// Class: nl/speyk/groepopdracht/GroepOpdrachtResourceJaxRs_c86d179e8a467f34aa831e3e57c2131c57abd49f$quarkusrestinvoker$update_2e1e202d038039119433d10b34f73586c5ce400c
//     Access =  public synthetic
//     Extends: java/lang/Object
//     Implements:
//         org/jboss/resteasy/reactive/server/spi/EndpointInvoker

// DO NOT MODIFY.  This is not actually a source file; it is a textual representation of generated code.
// Use only for debugging purposes.

// Auto-generated constructor
// Access: public
Method <init> : V
(
    // (no arguments)
) {
    ALOAD 0
    // Method descriptor: ()V
    INVOKESPECIAL java/lang/Object#<init>
    RETURN
    
}

// Access: public
Method invoke : Ljava/lang/Object;
(
    arg 1 = Ljava/lang/Object;,
    arg 2 = [Ljava/lang/Object;
) {
    ** label1
    ALOAD 2
    ICONST_0
    AALOAD
    ASTORE 3
    ALOAD 2
    ICONST_1
    AALOAD
    ASTORE 4
    ALOAD 2
    ICONST_2
    AALOAD
    ASTORE 5
    ALOAD 1
    CHECKCAST nl/speyk/groepopdracht/GroepOpdrachtResourceJaxRs_c86d179e8a467f34aa831e3e57c2131c57abd49f
    ALOAD 3
    CHECKCAST java/lang/Long
    ALOAD 4
    CHECKCAST nl/speyk/groepopdracht/GroepOpdracht
    ALOAD 5
    CHECKCAST jakarta/ws/rs/core/UriInfo
    // Method descriptor: (Ljava/lang/Long;Lnl/speyk/groepopdracht/GroepOpdracht;Ljakarta/ws/rs/core/UriInfo;)Lio/smallrye/mutiny/Uni;
    INVOKEVIRTUAL nl/speyk/groepopdracht/GroepOpdrachtResourceJaxRs_c86d179e8a467f34aa831e3e57c2131c57abd49f#update
    ARETURN
    ** label2
    
}

