// Class: io/quarkus/security/runtime/X509IdentityProvider_Bean
//     Access =  public synthetic
//     Extends: java/lang/Object
//     Implements:
//         io/quarkus/arc/InjectableBean
//         java/util/function/Supplier

// DO NOT MODIFY.  This is not actually a source file; it is a textual representation of generated code.
// Use only for debugging purposes.

// Access: private final
Field types : Ljava/util/Set;

// Access: public
Method <init> : V
(
    // (no arguments)
) {
    ** label1
    ALOAD 0
    // Method descriptor: ()V
    INVOKESPECIAL java/lang/Object#<init>
    // Method descriptor: ()Ljava/lang/Thread;
    INVOKESTATIC java/lang/Thread#currentThread
    // Method descriptor: ()Ljava/lang/ClassLoader;
    INVOKEVIRTUAL java/lang/Thread#getContextClassLoader
    ASTORE 1
    ICONST_3
    ANEWARRAY java/lang/Object
    ASTORE 5
    ICONST_1
    ANEWARRAY java/lang/reflect/Type
    ASTORE 2
    LDC (String) "io.quarkus.security.identity.request.CertificateAuthenticationRequest"
    ICONST_0
    ALOAD 1
    // Method descriptor: (Ljava/lang/String;ZLjava/lang/ClassLoader;)Ljava/lang/Class;
    INVOKESTATIC java/lang/Class#forName
    ASTORE 3
    ALOAD 2
    ICONST_0
    ALOAD 3
    CHECKCAST java/lang/reflect/Type
    AASTORE
    LDC (String) "io.quarkus.security.identity.IdentityProvider"
    ICONST_0
    ALOAD 1
    // Method descriptor: (Ljava/lang/String;ZLjava/lang/ClassLoader;)Ljava/lang/Class;
    INVOKESTATIC java/lang/Class#forName
    ASTORE 4
    NEW io/quarkus/arc/impl/ParameterizedTypeImpl
    DUP
    ALOAD 4
    CHECKCAST java/lang/reflect/Type
    ALOAD 2
    // Method descriptor: (Ljava/lang/reflect/Type;[Ljava/lang/reflect/Type;)V
    INVOKESPECIAL io/quarkus/arc/impl/ParameterizedTypeImpl#<init>
    ASTORE 6
    ALOAD 5
    ICONST_0
    ALOAD 6
    AASTORE
    LDC (String) "io.quarkus.security.runtime.X509IdentityProvider"
    ICONST_0
    ALOAD 1
    // Method descriptor: (Ljava/lang/String;ZLjava/lang/ClassLoader;)Ljava/lang/Class;
    INVOKESTATIC java/lang/Class#forName
    ASTORE 7
    ALOAD 5
    ICONST_1
    ALOAD 7
    AASTORE
    LDC (Type) Ljava/lang/Object;
    ASTORE 8
    ALOAD 5
    ICONST_2
    ALOAD 8
    AASTORE
    ALOAD 5
    // Method descriptor: ([Ljava/lang/Object;)Ljava/util/Set;
    INVOKESTATIC io/quarkus/arc/impl/Sets#of
    ASTORE 9
    ALOAD 0
    ALOAD 9
    // Field descriptor: Ljava/util/Set;
    PUTFIELD io/quarkus/security/runtime/X509IdentityProvider_Bean#types
    RETURN
    ** label2
    
}

// Access: public
Method getIdentifier : Ljava/lang/String;
(
    // (no arguments)
) {
    ** label1
    LDC (String) "a6ebd1a6abb08a5ea205dc7d0bb96045ffe06337"
    ARETURN
    ** label2
    
}

// Access: public
Method get : Ljava/lang/Object;
(
    // (no arguments)
) {
    ** label1
    ALOAD 0
    ARETURN
    ** label2
    
}

// Access: private
Method doCreate : Lio/quarkus/security/runtime/X509IdentityProvider;
(
    arg 1 = Ljakarta/enterprise/context/spi/CreationalContext;
) {
    ** label1
    NEW io/quarkus/security/runtime/X509IdentityProvider
    DUP
    // Method descriptor: ()V
    INVOKESPECIAL io/quarkus/security/runtime/X509IdentityProvider#<init>
    ARETURN
    ** label2
    
}

// Access: public
Method create : Lio/quarkus/security/runtime/X509IdentityProvider;
(
    arg 1 = Ljakarta/enterprise/context/spi/CreationalContext;
) {
    ** label1
    ** label2
    ALOAD 0
    ALOAD 1
    // Method descriptor: (Ljakarta/enterprise/context/spi/CreationalContext;)Lio/quarkus/security/runtime/X509IdentityProvider;
    INVOKESPECIAL io/quarkus/security/runtime/X509IdentityProvider_Bean#doCreate
    ARETURN
    ** label3
    GOTO label4
    ** label5
    ASTORE 2
    ALOAD 2
    INSTANCEOF java/lang/RuntimeException
    IFEQ label6
    ** label7
    ALOAD 2
    CHECKCAST java/lang/Throwable
    ATHROW
    ** label8
    GOTO label9
    ** label6
    ** label9
    NEW jakarta/enterprise/inject/CreationException
    DUP
    ALOAD 2
    CHECKCAST java/lang/Throwable
    // Method descriptor: (Ljava/lang/Throwable;)V
    INVOKESPECIAL jakarta/enterprise/inject/CreationException#<init>
    CHECKCAST java/lang/Throwable
    ATHROW
    ** label10
    GOTO label4
    // Try from label2 to label3
    // Catch java/lang/Exception by going to label5
    ** label4
    ** label11
    
}

// Access: public bridge
Method create : Ljava/lang/Object;
(
    arg 1 = Ljakarta/enterprise/context/spi/CreationalContext;
) {
    ** label1
    ALOAD 0
    ALOAD 1
    // Method descriptor: (Ljakarta/enterprise/context/spi/CreationalContext;)Lio/quarkus/security/runtime/X509IdentityProvider;
    INVOKEVIRTUAL io/quarkus/security/runtime/X509IdentityProvider_Bean#create
    ARETURN
    ** label2
    
}

// Access: public
Method get : Lio/quarkus/security/runtime/X509IdentityProvider;
(
    arg 1 = Ljakarta/enterprise/context/spi/CreationalContext;
) {
    ** label1
    // Method descriptor: ()Lio/quarkus/arc/ArcContainer;
    INVOKESTATIC io/quarkus/arc/Arc#container
    ASTORE 2
    NEW io/quarkus/arc/impl/CreationalContextImpl
    DUP
    ALOAD 0
    CHECKCAST jakarta/enterprise/context/spi/Contextual
    // Method descriptor: (Ljakarta/enterprise/context/spi/Contextual;)V
    INVOKESPECIAL io/quarkus/arc/impl/CreationalContextImpl#<init>
    ASTORE 3
    ALOAD 2
    LDC (Type) Ljakarta/inject/Singleton;
    // Method descriptor: (Ljava/lang/Class;)Lio/quarkus/arc/InjectableContext;
    INVOKEINTERFACE io/quarkus/arc/ArcContainer#getActiveContext
    CHECKCAST jakarta/enterprise/context/spi/Context
    ALOAD 0
    CHECKCAST jakarta/enterprise/context/spi/Contextual
    ALOAD 3
    CHECKCAST jakarta/enterprise/context/spi/CreationalContext
    // Method descriptor: (Ljakarta/enterprise/context/spi/Contextual;Ljakarta/enterprise/context/spi/CreationalContext;)Ljava/lang/Object;
    INVOKEINTERFACE jakarta/enterprise/context/spi/Context#get
    CHECKCAST io/quarkus/security/runtime/X509IdentityProvider
    ARETURN
    ** label2
    
}

// Access: public bridge
Method get : Ljava/lang/Object;
(
    arg 1 = Ljakarta/enterprise/context/spi/CreationalContext;
) {
    ** label1
    ALOAD 0
    ALOAD 1
    // Method descriptor: (Ljakarta/enterprise/context/spi/CreationalContext;)Lio/quarkus/security/runtime/X509IdentityProvider;
    INVOKEVIRTUAL io/quarkus/security/runtime/X509IdentityProvider_Bean#get
    ARETURN
    ** label2
    
}

// Access: public
Method getTypes : Ljava/util/Set;
(
    // (no arguments)
) {
    ** label1
    ALOAD 0
    // Field descriptor: Ljava/util/Set;
    GETFIELD io/quarkus/security/runtime/X509IdentityProvider_Bean#types
    ARETURN
    ** label2
    
}

// Access: public
Method getScope : Ljava/lang/Class;
(
    // (no arguments)
) {
    ** label1
    LDC (Type) Ljakarta/inject/Singleton;
    ARETURN
    ** label2
    
}

// Access: public
Method getBeanClass : Ljava/lang/Class;
(
    // (no arguments)
) {
    ** label1
    LDC (Type) Lio/quarkus/security/runtime/X509IdentityProvider;
    ARETURN
    ** label2
    
}

// Access: public
Method isSuppressed : Z
(
    // (no arguments)
) {
    ** label1
    ICONST_0
    IRETURN
    ** label2
    
}

// Access: public
Method equals : Z
(
    arg 1 = Ljava/lang/Object;
) {
    ** label1
    ALOAD 0
    ALOAD 1
    IF_ACMPEQ label2
    ** label3
    ** label4
    GOTO label5
    ** label2
    ICONST_1
    IRETURN
    ** label5
    ALOAD 1
    IFNULL label6
    ** label7
    ** label8
    GOTO label9
    ** label6
    ICONST_0
    IRETURN
    ** label9
    ALOAD 1
    INSTANCEOF io/quarkus/arc/InjectableBean
    IFEQ label10
    ** label11
    ** label12
    GOTO label13
    ** label10
    ICONST_0
    IRETURN
    ** label13
    ALOAD 1
    CHECKCAST io/quarkus/arc/InjectableBean
    // Method descriptor: ()Ljava/lang/String;
    INVOKEINTERFACE io/quarkus/arc/InjectableBean#getIdentifier
    ASTORE 2
    LDC (String) "a6ebd1a6abb08a5ea205dc7d0bb96045ffe06337"
    ALOAD 2
    // Method descriptor: (Ljava/lang/Object;)Z
    INVOKEVIRTUAL java/lang/Object#equals
    IRETURN
    ** label14
    
}

// Access: public
Method hashCode : I
(
    // (no arguments)
) {
    ** label1
    LDC (Integer) -2108850290
    IRETURN
    ** label2
    
}

// Access: public
Method toString : Ljava/lang/String;
(
    // (no arguments)
) {
    ** label1
    ALOAD 0
    CHECKCAST io/quarkus/arc/InjectableBean
    // Method descriptor: (Lio/quarkus/arc/InjectableBean;)Ljava/lang/String;
    INVOKESTATIC io/quarkus/arc/impl/Beans#toString
    ARETURN
    ** label2
    
}

