// Class: io/quarkus/deployment/steps/ArcProcessor$notifyBeanContainerListeners1304312071
//     Access =  public synthetic
//     Extends: java/lang/Object
//     Implements:
//         io/quarkus/runtime/StartupTask

// DO NOT MODIFY.  This is not actually a source file; it is a textual representation of generated code.
// Use only for debugging purposes.

// Auto-generated constructor
// Access: public
Method <init> : V
(
    // (no arguments)
) {
    ALOAD 0
    // Method descriptor: ()V
    INVOKESPECIAL java/lang/Object#<init>
    RETURN
    
}

// Access: public
Method deploy : V
(
    arg 1 = Lio/quarkus/runtime/StartupContext;
) {
    ** label1
    ALOAD 1
    LDC (String) "ArcProcessor.notifyBeanContainerListeners"
    // Method descriptor: (Ljava/lang/String;)V
    INVOKEVIRTUAL io/quarkus/runtime/StartupContext#setCurrentBuildStepName
    ALOAD 0
    // Method descriptor: ()[Ljava/lang/Object;
    INVOKEVIRTUAL io/quarkus/deployment/steps/ArcProcessor$notifyBeanContainerListeners1304312071#$quarkus$createArray
    ASTORE 2
    ALOAD 0
    ALOAD 1
    ALOAD 2
    // Method descriptor: (Lio/quarkus/runtime/StartupContext;[Ljava/lang/Object;)V
    INVOKEVIRTUAL io/quarkus/deployment/steps/ArcProcessor$notifyBeanContainerListeners1304312071#deploy_0
    RETURN
    ** label2
    
}

// Access: public
Method deploy_0 : V
(
    arg 1 = Lio/quarkus/runtime/StartupContext;,
    arg 2 = [Ljava/lang/Object;
) {
    ** label1
    NEW io/quarkus/arc/runtime/ArcRecorder
    DUP
    // Method descriptor: ()V
    INVOKESPECIAL io/quarkus/arc/runtime/ArcRecorder#<init>
    ASTORE 6
    NEW java/util/ArrayList
    DUP
    ICONST_2
    // Method descriptor: (I)V
    INVOKESPECIAL java/util/ArrayList#<init>
    ASTORE 3
    ALOAD 1
    LDC (String) "proxykey96"
    // Method descriptor: (Ljava/lang/String;)Ljava/lang/Object;
    INVOKEVIRTUAL io/quarkus/runtime/StartupContext#getValue
    ASTORE 4
    ALOAD 3
    CHECKCAST java/util/Collection
    ALOAD 4
    // Method descriptor: (Ljava/lang/Object;)Z
    INVOKEINTERFACE java/util/Collection#add
    POP
    ALOAD 1
    LDC (String) "proxykey146"
    // Method descriptor: (Ljava/lang/String;)Ljava/lang/Object;
    INVOKEVIRTUAL io/quarkus/runtime/StartupContext#getValue
    ASTORE 5
    ALOAD 3
    CHECKCAST java/util/Collection
    ALOAD 5
    // Method descriptor: (Ljava/lang/Object;)Z
    INVOKEINTERFACE java/util/Collection#add
    POP
    ALOAD 1
    LDC (String) "proxykey190"
    // Method descriptor: (Ljava/lang/String;)Ljava/lang/Object;
    INVOKEVIRTUAL io/quarkus/runtime/StartupContext#getValue
    ASTORE 7
    ALOAD 6
    ALOAD 7
    CHECKCAST io/quarkus/arc/ArcContainer
    ALOAD 3
    CHECKCAST java/util/List
    // Method descriptor: (Lio/quarkus/arc/ArcContainer;Ljava/util/List;)Lio/quarkus/arc/runtime/BeanContainer;
    INVOKEVIRTUAL io/quarkus/arc/runtime/ArcRecorder#initBeanContainer
    ASTORE 8
    ALOAD 1
    LDC (String) "proxykey192"
    ALOAD 8
    // Method descriptor: (Ljava/lang/String;Ljava/lang/Object;)V
    INVOKEVIRTUAL io/quarkus/runtime/StartupContext#putValue
    RETURN
    ** label2
    
}

// Access: public
Method $quarkus$createArray : [Ljava/lang/Object;
(
    // (no arguments)
) {
    ** label1
    ICONST_0
    ANEWARRAY java/lang/Object
    ARETURN
    ** label2
    
}

