// Class: io/quarkus/arc/setup/Default_ComponentsProvider$$function$$1
//     Access =  public synthetic
//     Extends: java/lang/Object
//     Implements:
//         java/util/function/Supplier

// DO NOT MODIFY.  This is not actually a source file; it is a textual representation of generated code.
// Use only for debugging purposes.

// Access: public
Method get : Ljava/lang/Object;
(
    // (no arguments)
) {
    ** label1
    ** label2
    NEW java/util/ArrayList
    DUP
    // Method descriptor: ()V
    INVOKESPECIAL java/util/ArrayList#<init>
    ASTORE 1
    NEW java/util/HashMap
    DUP
    // Method descriptor: ()V
    INVOKESPECIAL java/util/HashMap#<init>
    ASTORE 2
    ALOAD 1
    CHECKCAST java/util/List
    ALOAD 2
    CHECKCAST java/util/Map
    // Method descriptor: (Ljava/util/List;Ljava/util/Map;)V
    INVOKESTATIC io/quarkus/arc/setup/Default_ComponentsProvider#addRemovedBeans1
    ALOAD 1
    CHECKCAST java/util/List
    ALOAD 2
    CHECKCAST java/util/Map
    // Method descriptor: (Ljava/util/List;Ljava/util/Map;)V
    INVOKESTATIC io/quarkus/arc/setup/Default_ComponentsProvider#addRemovedBeans2
    ALOAD 1
    CHECKCAST java/util/List
    ALOAD 2
    CHECKCAST java/util/Map
    // Method descriptor: (Ljava/util/List;Ljava/util/Map;)V
    INVOKESTATIC io/quarkus/arc/setup/Default_ComponentsProvider#addRemovedBeans3
    ALOAD 1
    CHECKCAST java/util/List
    ALOAD 2
    CHECKCAST java/util/Map
    // Method descriptor: (Ljava/util/List;Ljava/util/Map;)V
    INVOKESTATIC io/quarkus/arc/setup/Default_ComponentsProvider#addRemovedBeans4
    ALOAD 1
    CHECKCAST java/util/List
    ALOAD 2
    CHECKCAST java/util/Map
    // Method descriptor: (Ljava/util/List;Ljava/util/Map;)V
    INVOKESTATIC io/quarkus/arc/setup/Default_ComponentsProvider#addRemovedBeans5
    ALOAD 1
    CHECKCAST java/util/List
    ALOAD 2
    CHECKCAST java/util/Map
    // Method descriptor: (Ljava/util/List;Ljava/util/Map;)V
    INVOKESTATIC io/quarkus/arc/setup/Default_ComponentsProvider#addRemovedBeans6
    ALOAD 1
    CHECKCAST java/util/List
    ALOAD 2
    CHECKCAST java/util/Map
    // Method descriptor: (Ljava/util/List;Ljava/util/Map;)V
    INVOKESTATIC io/quarkus/arc/setup/Default_ComponentsProvider#addRemovedBeans7
    ALOAD 1
    CHECKCAST java/util/List
    ALOAD 2
    CHECKCAST java/util/Map
    // Method descriptor: (Ljava/util/List;Ljava/util/Map;)V
    INVOKESTATIC io/quarkus/arc/setup/Default_ComponentsProvider#addRemovedBeans8
    ALOAD 1
    CHECKCAST java/util/List
    ALOAD 2
    CHECKCAST java/util/Map
    // Method descriptor: (Ljava/util/List;Ljava/util/Map;)V
    INVOKESTATIC io/quarkus/arc/setup/Default_ComponentsProvider#addRemovedBeans9
    ALOAD 1
    CHECKCAST java/util/List
    ALOAD 2
    CHECKCAST java/util/Map
    // Method descriptor: (Ljava/util/List;Ljava/util/Map;)V
    INVOKESTATIC io/quarkus/arc/setup/Default_ComponentsProvider#addRemovedBeans10
    ALOAD 1
    CHECKCAST java/util/List
    ALOAD 2
    CHECKCAST java/util/Map
    // Method descriptor: (Ljava/util/List;Ljava/util/Map;)V
    INVOKESTATIC io/quarkus/arc/setup/Default_ComponentsProvider#addRemovedBeans11
    ALOAD 1
    CHECKCAST java/util/List
    ALOAD 2
    CHECKCAST java/util/Map
    // Method descriptor: (Ljava/util/List;Ljava/util/Map;)V
    INVOKESTATIC io/quarkus/arc/setup/Default_ComponentsProvider#addRemovedBeans12
    ALOAD 1
    CHECKCAST java/util/List
    ALOAD 2
    CHECKCAST java/util/Map
    // Method descriptor: (Ljava/util/List;Ljava/util/Map;)V
    INVOKESTATIC io/quarkus/arc/setup/Default_ComponentsProvider#addRemovedBeans13
    ALOAD 1
    CHECKCAST java/util/List
    ALOAD 2
    CHECKCAST java/util/Map
    // Method descriptor: (Ljava/util/List;Ljava/util/Map;)V
    INVOKESTATIC io/quarkus/arc/setup/Default_ComponentsProvider#addRemovedBeans14
    ALOAD 1
    CHECKCAST java/util/List
    ALOAD 2
    CHECKCAST java/util/Map
    // Method descriptor: (Ljava/util/List;Ljava/util/Map;)V
    INVOKESTATIC io/quarkus/arc/setup/Default_ComponentsProvider#addRemovedBeans15
    ALOAD 1
    CHECKCAST java/util/List
    ALOAD 2
    CHECKCAST java/util/Map
    // Method descriptor: (Ljava/util/List;Ljava/util/Map;)V
    INVOKESTATIC io/quarkus/arc/setup/Default_ComponentsProvider#addRemovedBeans16
    ALOAD 1
    ARETURN
    ** label3
    ** label4
    
}

// Access: public
Method <init> : V
(
    // (no arguments)
) {
    ** label1
    ALOAD 0
    // Method descriptor: ()V
    INVOKESPECIAL java/lang/Object#<init>
    RETURN
    ** label2
    
}

